CHANGES.txt
LICENSE.txt
MANIFEST.in
README.md
setup.py
docs/background.md
virtualecologist/__init__.py
virtualecologist/virtualecologist.py
virtualecologist.egg-info/PKG-INFO
virtualecologist.egg-info/SOURCES.txt
virtualecologist.egg-info/dependency_links.txt
virtualecologist.egg-info/requires.txt
virtualecologist.egg-info/top_level.txt
virtualecologist/data/fulldata.csv
virtualecologist/data/pilotdata.csv