Metadata-Version: 1.1
Name: virtualecologist
Version: 0.0.5
Summary: Optimize transect length in ecological surveys.
Home-page: https://github.com/rayblick/Virtual-Ecologist
Author: Ray
Author-email: rblick.ecol@gmail.com
License: MIT
Keywords: ecology,environment,conservation,modelling
Platform: UNKNOWN
Classifier: Development Status :: 3 - Alpha
Classifier: Natural Language :: English
Classifier: Programming Language :: Python :: 2.7
Classifier: Topic :: Scientific/Engineering
Classifier: Topic :: Scientific/Engineering :: Visualization
Classifier: Topic :: Scientific/Engineering :: Bio-Informatics
